{
    "sourceFile": "assets/configJson/prod/t2/t2-02.json",
    "activeCommit": 0,
    "commits": [
        {
            "activePatchIndex": 3,
            "patches": [
                {
                    "date": 1623994460686,
                    "content": "Index: \n===================================================================\n--- \n+++ \n"
                },
                {
                    "date": 1623994503375,
                    "content": "Index: \n===================================================================\n--- \n+++ \n@@ -43,9 +43,11 @@\n                      \"gu\": {\"x\": 495, \"y\": 200, \"width\":260, \"height\": 220},\r\n                       \"shachui\": {\"x\": 1205, \"y\": 190, \"width\":260, \"height\": 220}, \r\n                       \"dizi\": {\"x\": 850, \"y\": 440, \"width\":260, \"height\": 220}, \r\n                       \"sanjiaotie\": {\"x\": 520, \"y\": 695, \"width\":260, \"height\": 220}\r\n-                    }\r\n+                    },\r\n+\r\n+                    \"guideName\": \"shachui\"\r\n                 }\r\n             }, \r\n             \r\n             \"components\": {\r\n@@ -62,15 +64,19 @@\n                 \"bundleName\": \"choose\",\r\n                 \"prefabName\": \"choose-model03-v1\",\r\n                 \"config\": {\r\n \r\n+                    \"soundFile\": {\"piano\": \"ui://733aoo45bl377s\", \"gu\": \"ui://733aoo45bl377p\", \"shachui\": \"ui://733aoo45bl377o\", \"dizi\": \"ui://733aoo45bl377n\", \"sanjiaotie\": \"ui://733aoo45bl377r\" },\r\n+                    \"rightSoundFile\": [\"ui://733aoo45bl377s\", \"ui://733aoo45bl377p\"],\r\n+\r\n                     \"rightName\": [\"piano\", \"gu\"],\r\n \r\n                     \"optionsRect\": {\"piano\": {\"x\": 1205, \"y\": 190, \"width\":260, \"height\": 220},\r\n                      \"gu\": {\"x\": 850, \"y\": 440, \"width\":260, \"height\": 220},\r\n                       \"shachui\": {\"x\": 520, \"y\": 695, \"width\":260, \"height\": 220}, \r\n                       \"dizi\": {\"x\": 1237, \"y\": 653, \"width\":260, \"height\": 220}, \r\n-                      \"sanjiaotie\": {\"x\": 495, \"y\": 200, \"width\":260, \"height\": 220}}\r\n+                      \"sanjiaotie\": {\"x\": 495, \"y\": 200, \"width\":260, \"height\": 220}},\r\n+                      \"guideName\": \"piano\"\r\n                 }\r\n             }, \r\n             \r\n             \"components\": {\r\n@@ -86,15 +92,18 @@\n                 \"uiPath\": \"choose-model03-v1-p4\",\r\n                 \"bundleName\": \"choose\",\r\n                 \"prefabName\": \"choose-model03-v1\",\r\n                 \"config\": {\r\n+                    \"soundFile\": {\"piano\": \"ui://733aoo45bl377u\", \"gu\": \"ui://733aoo45bl377v\", \"shachui\": \"ui://733aoo45bl377t\", \"dizi\": \"ui://733aoo45bl377w\", \"sanjiaotie\": \"ui://733aoo45bl377y\" },\r\n+                    \"rightSoundFile\": [\"ui://733aoo45bl377u\", \"ui://733aoo45bl377v\"],\r\n                     \r\n                     \"rightName\": [\"piano\", \"gu\"],\r\n                     \"optionsRect\": {\"piano\": {\"x\": 850, \"y\": 440, \"width\":260, \"height\": 220}, \r\n                      \"gu\": {\"x\": 520, \"y\": 695, \"width\":260, \"height\": 220},\r\n                       \"shachui\": {\"x\": 495, \"y\": 200, \"width\":260, \"height\": 220}, \r\n                       \"dizi\": {\"x\": 1205, \"y\": 190, \"width\":260, \"height\": 220}, \r\n-                      \"sanjiaotie\": {\"x\": 1237, \"y\": 653, \"width\":260, \"height\": 220}}\r\n+                      \"sanjiaotie\": {\"x\": 1237, \"y\": 653, \"width\":260, \"height\": 220}},\r\n+                      \"guideName\": \"dizi\"\r\n                 }\r\n             }, \r\n             \r\n             \"components\": {\r\n@@ -267,6 +276,7 @@\n               \"prefabName\": \"static-model01-v1\"\r\n             }\r\n           }\r\n \r\n+\r\n     ]\r\n }\n\\ No newline at end of file\n"
                },
                {
                    "date": 1623994634889,
                    "content": "Index: \n===================================================================\n--- \n+++ \n@@ -0,0 +1,282 @@\n+{\r\n+    \"name\": \"数理思维\",\r\n+    \"courseName\": \"t2-02\",\r\n+    \"env\": \"test\",\r\n+    \"totalPages\": 12,\r\n+    \"pathConfig\": {\r\n+        \"remoteUrl\": \"https://6166-after-school-review-8cguaeaace9d-1304725138.tcb.qcloud.la/\",\r\n+        \"controllerBundlePath\": \"T-series/prefabLibrary/controllers/\",\r\n+        \"controllerName\": \"controller-model02\",\r\n+        \"resourceBundlePath\": \"T-series/fairyUis/t2/\",\r\n+        \"panelBundlePath\": \"T-series/prefabLibrary/components/\",\r\n+        \"panelName\": \"formal-panle-model02\",\r\n+        \"modelBundlePath\": \"T-series/prefabLibrary/models/\",\r\n+        \"componentBundlePath\": \"T-series/prefabLibrary/components/\",\r\n+        \"resourceName\": \"t2-02\",\r\n+        \"packageName\": \"t2-02\"\r\n+    },\r\n+    \"chapters\": [ \r\n+        \r\n+        {\r\n+            \"model\": {\r\n+              \"uiPath\": \"static-model01-v1-p1\",\r\n+              \"bundleName\": \"static\",\r\n+              \"prefabName\": \"static-model01-v1\"\r\n+            }\r\n+        },\r\n+\r\n+        {\r\n+            \"model\": {\r\n+                \"uiPath\": \"choose-model03-v1-p2\",\r\n+                \"bundleName\": \"choose\",\r\n+                \"prefabName\": \"choose-model03-v1\",\r\n+                \"config\": {\r\n+                    \"isAnimateShow\": true,\r\n+                    \"soundFile\": {\"piano\": \"ui://733aoo45w2qd18\", \"gu\": \"ui://733aoo45w2qd16\", \"shachui\": \"ui://733aoo45w2qd1a\", \"dizi\": \"ui://733aoo45w2qd17\", \"sanjiaotie\": \"ui://733aoo45w2qd19\" },\r\n+                    \"rightSoundFile\": [\"ui://733aoo45w2qd18\", \"ui://733aoo45w2qd16\"],\r\n+                    \"animateName\":{\"piano\": {\"idle\": \"05gangqin_idle\", \"play\": \"05gangqin_play\", \"skin\": \"05gangqin\"},\"gu\": {\"idle\": \"01gu_idle\", \"play\": \"01gu_play\", \"skin\": \"01gu\"},\"shachui\": {\"idle\": \"02shacui_idle\", \"play\": \"02shacui_play\", \"skin\": \"02shacui\"},\r\n+                    \"dizi\": {\"idle\": \"03dizi_idle\", \"play\": \"03dizi_play\", \"skin\": \"03dizi\"},\r\n+                    \"sanjiaotie\": {\"idle\": \"04qiaojibang_idle\", \"play\": \"04qiaojibang_play\", \"skin\": \"04qiaojibang\"}},\r\n+                    \"rightName\": [\"piano\", \"gu\"],\r\n+                    \"optionsRect\":{\r\n+                     \"piano\": {\"x\": 1237, \"y\": 653, \"width\":260, \"height\": 220},\r\n+                     \"gu\": {\"x\": 495, \"y\": 200, \"width\":260, \"height\": 220},\r\n+                      \"shachui\": {\"x\": 1205, \"y\": 190, \"width\":260, \"height\": 220}, \r\n+                      \"dizi\": {\"x\": 850, \"y\": 440, \"width\":260, \"height\": 220}, \r\n+                      \"sanjiaotie\": {\"x\": 520, \"y\": 695, \"width\":260, \"height\": 220}\r\n+                    },\r\n+\r\n+                    \"guideName\": \"shachui\"\r\n+                }\r\n+            }, \r\n+            \r\n+            \"components\": {\r\n+                \"feedback\": {\r\n+                    \"bundleName\": \"feedback\",\r\n+                    \"prefabName\": \"feedback-model01-v1\"\r\n+                }\r\n+            }\r\n+        },\r\n+\r\n+        {\r\n+            \"model\": {\r\n+                \"uiPath\": \"choose-model03-v1-p3\",\r\n+                \"bundleName\": \"choose\",\r\n+                \"prefabName\": \"choose-model03-v1\",\r\n+                \"config\": {\r\n+\r\n+                    \"soundFile\": {\"piano\": \"ui://733aoo45bl377s\", \"gu\": \"ui://733aoo45bl377p\", \"shachui\": \"ui://733aoo45bl377o\", \"dizi\": \"ui://733aoo45bl377n\", \"sanjiaotie\": \"ui://733aoo45bl377r\" },\r\n+                    \"rightSoundFile\": [\"ui://733aoo45bl377s\", \"ui://733aoo45bl377p\"],\r\n+\r\n+                    \"rightName\": [\"piano\", \"gu\"],\r\n+\r\n+                    \"optionsRect\": {\"piano\": {\"x\": 1205, \"y\": 190, \"width\":260, \"height\": 220},\r\n+                     \"gu\": {\"x\": 850, \"y\": 440, \"width\":260, \"height\": 220},\r\n+                      \"shachui\": {\"x\": 520, \"y\": 695, \"width\":260, \"height\": 220}, \r\n+                      \"dizi\": {\"x\": 1237, \"y\": 653, \"width\":260, \"height\": 220}, \r\n+                      \"sanjiaotie\": {\"x\": 495, \"y\": 200, \"width\":260, \"height\": 220}},\r\n+                      \"guideName\": \"piano\"\r\n+                }\r\n+            }, \r\n+            \r\n+            \"components\": {\r\n+                \"feedback\": {\r\n+                    \"bundleName\": \"feedback\",\r\n+                    \"prefabName\": \"feedback-model01-v1\"\r\n+                }\r\n+            }\r\n+        },\r\n+\r\n+        {\r\n+            \"model\": {\r\n+                \"uiPath\": \"choose-model03-v1-p4\",\r\n+                \"bundleName\": \"choose\",\r\n+                \"prefabName\": \"choose-model03-v1\",\r\n+                \"config\": {\r\n+                    \"soundFile\": {\"piano\": \"ui://733aoo45bl377u\", \"gu\": \"ui://733aoo45bl377v\", \"shachui\": \"ui://733aoo45bl377t\", \"dizi\": \"ui://733aoo45bl377w\", \"sanjiaotie\": \"ui://733aoo45bl377y\" },\r\n+                    \"rightSoundFile\": [\"ui://733aoo45bl377u\", \"ui://733aoo45bl377v\"],\r\n+                    \r\n+                    \"rightName\": [\"piano\", \"gu\"],\r\n+                    \"optionsRect\": {\"piano\": {\"x\": 850, \"y\": 440, \"width\":260, \"height\": 220}, \r\n+                     \"gu\": {\"x\": 520, \"y\": 695, \"width\":260, \"height\": 220},\r\n+                      \"shachui\": {\"x\": 495, \"y\": 200, \"width\":260, \"height\": 220}, \r\n+                      \"dizi\": {\"x\": 1205, \"y\": 190, \"width\":260, \"height\": 220}, \r\n+                      \"sanjiaotie\": {\"x\": 1237, \"y\": 653, \"width\":260, \"height\": 220}},\r\n+                      \"guideName\": \"dizi\"\r\n+                }\r\n+            }, \r\n+            \r\n+            \"components\": {\r\n+                \"feedback\": {\r\n+                    \"bundleName\": \"feedback\",\r\n+                    \"prefabName\": \"feedback-model01-v1\"\r\n+                }\r\n+            }\r\n+        },\r\n+\r\n+        {\r\n+            \"model\": {\r\n+                \"uiPath\": \"choose-model03-v2-p5\",\r\n+                \"bundleName\": \"choose\",\r\n+                \"prefabName\": \"choose-model03-v2\",\r\n+                \"config\": {\r\n+                    \"gameFood\": [\"food_1\", \"food_2\", \"food_3\", \"food_4\"],\r\n+                    \"rightIndexs\": [0, 1],\r\n+                    \"boySoundPath\": \"ui://733aoo45w2qd1c\",\r\n+                    \"girlSoundPath\": \"ui://733aoo45w2qd1d\"\r\n+                    \r\n+                }\r\n+            }, \r\n+            \r\n+            \"components\": {\r\n+                \"feedback\": {\r\n+                    \"bundleName\": \"feedback\",\r\n+                    \"prefabName\": \"feedback-model01-v1\"\r\n+                }\r\n+            }\r\n+        },\r\n+\r\n+        {\r\n+            \"model\": {\r\n+                \"uiPath\": \"choose-model03-v2-p6\",\r\n+                \"bundleName\": \"choose\",\r\n+                \"prefabName\": \"choose-model03-v2\",\r\n+                \"config\": {\r\n+                    \"gameFood\": [\"food_1_1\", \"food_2_1\", \"food_3_1\"],\r\n+                    \"rightIndexs\": [0],\r\n+                    \"boySoundPath\": \"ui://733aoo45gzaz7e\",\r\n+                    \"girlSoundPath\": \"ui://733aoo45gzaz7f\"\r\n+                    \r\n+                }\r\n+            }, \r\n+            \r\n+            \"components\": {\r\n+                \"feedback\": {\r\n+                    \"bundleName\": \"feedback\",\r\n+                    \"prefabName\": \"feedback-model01-v1\"\r\n+                }\r\n+            }\r\n+        },\r\n+\r\n+        {\r\n+            \"model\": {\r\n+                \"uiPath\": \"choose-model03-v2-p7\",\r\n+                \"bundleName\": \"choose\",\r\n+                \"prefabName\": \"choose-model03-v2\",\r\n+                \"config\": {\r\n+\r\n+                    \"gameFood\": [\"food_1_2\", \"food_2_2\", \"food_3_2\"],\r\n+                    \"rightIndexs\": [1],\r\n+                    \"boySoundPath\": \"ui://733aoo45gzaz7g\",\r\n+                    \"girlSoundPath\": \"ui://733aoo45gzaz7h\"\r\n+                    \r\n+                }\r\n+            }, \r\n+            \r\n+            \"components\": {\r\n+                \"feedback\": {\r\n+                    \"bundleName\": \"feedback\",\r\n+                    \"prefabName\": \"feedback-model01-v1\"\r\n+                }\r\n+            }\r\n+        },\r\n+\r\n+        {\r\n+            \"model\": {\r\n+                \"uiPath\": \"choose-model03-v2-p8\",\r\n+                \"bundleName\": \"choose\",\r\n+                \"prefabName\": \"choose-model03-v3\",\r\n+                \"config\": {\r\n+\r\n+                    \"boxSoundUrl\": \"ui://733aoo45w2qd1f\",\r\n+                    \"guidIndex\": 2\r\n+                    \r\n+                }\r\n+            }, \r\n+            \r\n+            \"components\": {\r\n+                \"feedback\": {\r\n+                    \"bundleName\": \"feedback\",\r\n+                    \"prefabName\": \"feedback-model01-v1\"\r\n+                }\r\n+            }\r\n+        },\r\n+\r\n+\r\n+        {\r\n+            \"model\": {\r\n+                \"uiPath\": \"choose-model03-v2-p9\",\r\n+                \"bundleName\": \"choose\",\r\n+                \"prefabName\": \"choose-model03-v3\",\r\n+                \"config\": {\r\n+\r\n+                    \"boxSoundUrl\": \"ui://733aoo45gzaz7i\",\r\n+                    \"guidIndex\": 2\r\n+                    \r\n+                }\r\n+            }, \r\n+            \r\n+            \"components\": {\r\n+                \"feedback\": {\r\n+                    \"bundleName\": \"feedback\",\r\n+                    \"prefabName\": \"feedback-model01-v1\"\r\n+                }\r\n+            }\r\n+        },\r\n+\r\n+        {\r\n+            \"model\": {\r\n+                \"uiPath\": \"choose-model03-v2-p10\",\r\n+                \"bundleName\": \"choose\",\r\n+                \"prefabName\": \"choose-model03-v3\",\r\n+                \"config\": {\r\n+\r\n+                    \"boxSoundUrl\": \"ui://733aoo45gzaz7j\",\r\n+\r\n+                    \"guidIndex\": 0\r\n+                    \r\n+                }\r\n+            }, \r\n+            \r\n+            \"components\": {\r\n+                \"feedback\": {\r\n+                    \"bundleName\": \"feedback\",\r\n+                    \"prefabName\": \"feedback-model01-v1\"\r\n+                }\r\n+            }\r\n+        },\r\n+\r\n+        \r\n+        {\r\n+            \"model\": {\r\n+                \"uiPath\": \"choose-model03-v2-p11\",\r\n+                \"bundleName\": \"choose\",\r\n+                \"prefabName\": \"choose-model03-v3\",\r\n+                \"config\": {\r\n+\r\n+                    \"boxSoundUrl\": \"ui://733aoo45w2qd23\",\r\n+\r\n+                    \"guidIndex\": 1\r\n+                    \r\n+                }\r\n+            }, \r\n+            \r\n+            \"components\": {\r\n+                \"feedback\": {\r\n+                    \"bundleName\": \"feedback\",\r\n+                    \"prefabName\": \"feedback-model01-v1\"\r\n+                }\r\n+            }\r\n+        },\r\n+\r\n+        {\r\n+            \"model\": {\r\n+              \"uiPath\": \"static-model01-v1-p12\",\r\n+              \"bundleName\": \"static\",\r\n+              \"prefabName\": \"static-model01-v1\"\r\n+            }\r\n+          }\r\n+\r\n+\r\n+    ]\r\n+}\n\\ No newline at end of file\n"
                },
                {
                    "date": 1623996004113,
                    "content": "Index: \n===================================================================\n--- \n+++ \n@@ -0,0 +1,282 @@\n+{\r\n+    \"name\": \"数理思维\",\r\n+    \"courseName\": \"t2-02\",\r\n+    \"env\": \"test\",\r\n+    \"totalPages\": 12,\r\n+    \"pathConfig\": { \r\n+        \"remoteUrl\": \"https://6166-after-school-review-8cguaeaace9d-1304725138.tcb.qcloud.la/\",\r\n+        \"controllerBundlePath\": \"T-series/prefabLibrary/controllers/\",\r\n+        \"controllerName\": \"controller-model02\",\r\n+        \"resourceBundlePath\": \"T-series/fairyUis/t2/\",\r\n+        \"panelBundlePath\": \"T-series/prefabLibrary/components/\",\r\n+        \"panelName\": \"formal-panle-model02\",\r\n+        \"modelBundlePath\": \"T-series/prefabLibrary/models/\",\r\n+        \"componentBundlePath\": \"T-series/prefabLibrary/components/\",\r\n+        \"resourceName\": \"t2-02\",\r\n+        \"packageName\": \"t2-02\"\r\n+    },\r\n+    \"chapters\": [ \r\n+        \r\n+        {\r\n+            \"model\": {\r\n+              \"uiPath\": \"static-model01-v1-p1\",\r\n+              \"bundleName\": \"static\",\r\n+              \"prefabName\": \"static-model01-v1\"\r\n+            }\r\n+        },\r\n+\r\n+        {\r\n+            \"model\": {\r\n+                \"uiPath\": \"choose-model03-v1-p2\",\r\n+                \"bundleName\": \"choose\",\r\n+                \"prefabName\": \"choose-model03-v1\",\r\n+                \"config\": {\r\n+                    \"isAnimateShow\": true,\r\n+                    \"soundFile\": {\"piano\": \"ui://733aoo45w2qd18\", \"gu\": \"ui://733aoo45w2qd16\", \"shachui\": \"ui://733aoo45w2qd1a\", \"dizi\": \"ui://733aoo45w2qd17\", \"sanjiaotie\": \"ui://733aoo45w2qd19\" },\r\n+                    \"rightSoundFile\": [\"ui://733aoo45w2qd18\", \"ui://733aoo45w2qd16\"],\r\n+                    \"animateName\":{\"piano\": {\"idle\": \"05gangqin_idle\", \"play\": \"05gangqin_play\", \"skin\": \"05gangqin\"},\"gu\": {\"idle\": \"01gu_idle\", \"play\": \"01gu_play\", \"skin\": \"01gu\"},\"shachui\": {\"idle\": \"02shacui_idle\", \"play\": \"02shacui_play\", \"skin\": \"02shacui\"},\r\n+                    \"dizi\": {\"idle\": \"03dizi_idle\", \"play\": \"03dizi_play\", \"skin\": \"03dizi\"},\r\n+                    \"sanjiaotie\": {\"idle\": \"04qiaojibang_idle\", \"play\": \"04qiaojibang_play\", \"skin\": \"04qiaojibang\"}},\r\n+                    \"rightName\": [\"piano\", \"gu\"],\r\n+                    \"optionsRect\":{\r\n+                     \"piano\": {\"x\": 1237, \"y\": 653, \"width\":260, \"height\": 220},\r\n+                     \"gu\": {\"x\": 495, \"y\": 200, \"width\":260, \"height\": 220},\r\n+                      \"shachui\": {\"x\": 1205, \"y\": 190, \"width\":260, \"height\": 220}, \r\n+                      \"dizi\": {\"x\": 850, \"y\": 440, \"width\":260, \"height\": 220}, \r\n+                      \"sanjiaotie\": {\"x\": 520, \"y\": 695, \"width\":260, \"height\": 220}\r\n+                    },\r\n+\r\n+                    \"guideName\": \"shachui\"\r\n+                }\r\n+            }, \r\n+            \r\n+            \"components\": {\r\n+                \"feedback\": {\r\n+                    \"bundleName\": \"feedback\",\r\n+                    \"prefabName\": \"feedback-model01-v1\"\r\n+                }\r\n+            }\r\n+        },\r\n+\r\n+        {\r\n+            \"model\": {\r\n+                \"uiPath\": \"choose-model03-v1-p3\",\r\n+                \"bundleName\": \"choose\",\r\n+                \"prefabName\": \"choose-model03-v1\",\r\n+                \"config\": {\r\n+\r\n+                    \"soundFile\": {\"piano\": \"ui://733aoo45bl377s\", \"gu\": \"ui://733aoo45bl377p\", \"shachui\": \"ui://733aoo45bl377o\", \"dizi\": \"ui://733aoo45bl377n\", \"sanjiaotie\": \"ui://733aoo45bl377r\" },\r\n+                    \"rightSoundFile\": [\"ui://733aoo45bl377s\", \"ui://733aoo45bl377p\"],\r\n+\r\n+                    \"rightName\": [\"piano\", \"gu\"],\r\n+\r\n+                    \"optionsRect\": {\"piano\": {\"x\": 1205, \"y\": 190, \"width\":260, \"height\": 220},\r\n+                     \"gu\": {\"x\": 850, \"y\": 440, \"width\":260, \"height\": 220},\r\n+                      \"shachui\": {\"x\": 520, \"y\": 695, \"width\":260, \"height\": 220}, \r\n+                      \"dizi\": {\"x\": 1237, \"y\": 653, \"width\":260, \"height\": 220}, \r\n+                      \"sanjiaotie\": {\"x\": 495, \"y\": 200, \"width\":260, \"height\": 220}},\r\n+                      \"guideName\": \"piano\"\r\n+                }\r\n+            }, \r\n+            \r\n+            \"components\": {\r\n+                \"feedback\": {\r\n+                    \"bundleName\": \"feedback\",\r\n+                    \"prefabName\": \"feedback-model01-v1\"\r\n+                }\r\n+            }\r\n+        },\r\n+\r\n+        {\r\n+            \"model\": {\r\n+                \"uiPath\": \"choose-model03-v1-p4\",\r\n+                \"bundleName\": \"choose\",\r\n+                \"prefabName\": \"choose-model03-v1\",\r\n+                \"config\": {\r\n+                    \"soundFile\": {\"piano\": \"ui://733aoo45bl377u\", \"gu\": \"ui://733aoo45bl377v\", \"shachui\": \"ui://733aoo45bl377t\", \"dizi\": \"ui://733aoo45bl377w\", \"sanjiaotie\": \"ui://733aoo45bl377y\" },\r\n+                    \"rightSoundFile\": [\"ui://733aoo45bl377u\", \"ui://733aoo45bl377v\"],\r\n+                    \r\n+                    \"rightName\": [\"piano\", \"gu\"],\r\n+                    \"optionsRect\": {\"piano\": {\"x\": 850, \"y\": 440, \"width\":260, \"height\": 220}, \r\n+                     \"gu\": {\"x\": 520, \"y\": 695, \"width\":260, \"height\": 220},\r\n+                      \"shachui\": {\"x\": 495, \"y\": 200, \"width\":260, \"height\": 220}, \r\n+                      \"dizi\": {\"x\": 1205, \"y\": 190, \"width\":260, \"height\": 220}, \r\n+                      \"sanjiaotie\": {\"x\": 1237, \"y\": 653, \"width\":260, \"height\": 220}},\r\n+                      \"guideName\": \"dizi\"\r\n+                }\r\n+            }, \r\n+            \r\n+            \"components\": {\r\n+                \"feedback\": {\r\n+                    \"bundleName\": \"feedback\",\r\n+                    \"prefabName\": \"feedback-model01-v1\"\r\n+                }\r\n+            }\r\n+        },\r\n+\r\n+        {\r\n+            \"model\": {\r\n+                \"uiPath\": \"choose-model03-v2-p5\",\r\n+                \"bundleName\": \"choose\",\r\n+                \"prefabName\": \"choose-model03-v2\",\r\n+                \"config\": {\r\n+                    \"gameFood\": [\"food_1\", \"food_2\", \"food_3\", \"food_4\"],\r\n+                    \"rightIndexs\": [0, 1],\r\n+                    \"boySoundPath\": \"ui://733aoo45w2qd1c\",\r\n+                    \"girlSoundPath\": \"ui://733aoo45w2qd1d\"\r\n+                    \r\n+                }\r\n+            }, \r\n+            \r\n+            \"components\": {\r\n+                \"feedback\": {\r\n+                    \"bundleName\": \"feedback\",\r\n+                    \"prefabName\": \"feedback-model01-v1\"\r\n+                }\r\n+            }\r\n+        },\r\n+\r\n+        {\r\n+            \"model\": {\r\n+                \"uiPath\": \"choose-model03-v2-p6\",\r\n+                \"bundleName\": \"choose\",\r\n+                \"prefabName\": \"choose-model03-v2\",\r\n+                \"config\": {\r\n+                    \"gameFood\": [\"food_1_1\", \"food_2_1\", \"food_3_1\"],\r\n+                    \"rightIndexs\": [0],\r\n+                    \"boySoundPath\": \"ui://733aoo45gzaz7e\",\r\n+                    \"girlSoundPath\": \"ui://733aoo45gzaz7f\"\r\n+                    \r\n+                }\r\n+            }, \r\n+            \r\n+            \"components\": {\r\n+                \"feedback\": {\r\n+                    \"bundleName\": \"feedback\",\r\n+                    \"prefabName\": \"feedback-model01-v1\"\r\n+                }\r\n+            }\r\n+        },\r\n+\r\n+        {\r\n+            \"model\": {\r\n+                \"uiPath\": \"choose-model03-v2-p7\",\r\n+                \"bundleName\": \"choose\",\r\n+                \"prefabName\": \"choose-model03-v2\",\r\n+                \"config\": {\r\n+\r\n+                    \"gameFood\": [\"food_1_2\", \"food_2_2\", \"food_3_2\"],\r\n+                    \"rightIndexs\": [1],\r\n+                    \"boySoundPath\": \"ui://733aoo45gzaz7g\",\r\n+                    \"girlSoundPath\": \"ui://733aoo45gzaz7h\"\r\n+                    \r\n+                }\r\n+            }, \r\n+            \r\n+            \"components\": {\r\n+                \"feedback\": {\r\n+                    \"bundleName\": \"feedback\",\r\n+                    \"prefabName\": \"feedback-model01-v1\"\r\n+                }\r\n+            }\r\n+        },\r\n+\r\n+        {\r\n+            \"model\": {\r\n+                \"uiPath\": \"choose-model03-v2-p8\",\r\n+                \"bundleName\": \"choose\",\r\n+                \"prefabName\": \"choose-model03-v3\",\r\n+                \"config\": {\r\n+\r\n+                    \"boxSoundUrl\": \"ui://733aoo45w2qd1f\",\r\n+                    \"guidIndex\": 2\r\n+                    \r\n+                }\r\n+            }, \r\n+            \r\n+            \"components\": {\r\n+                \"feedback\": {\r\n+                    \"bundleName\": \"feedback\",\r\n+                    \"prefabName\": \"feedback-model01-v1\"\r\n+                }\r\n+            }\r\n+        },\r\n+\r\n+\r\n+        {\r\n+            \"model\": {\r\n+                \"uiPath\": \"choose-model03-v2-p9\",\r\n+                \"bundleName\": \"choose\",\r\n+                \"prefabName\": \"choose-model03-v3\",\r\n+                \"config\": {\r\n+\r\n+                    \"boxSoundUrl\": \"ui://733aoo45gzaz7i\",\r\n+                    \"guidIndex\": 2\r\n+                    \r\n+                }\r\n+            }, \r\n+            \r\n+            \"components\": {\r\n+                \"feedback\": {\r\n+                    \"bundleName\": \"feedback\",\r\n+                    \"prefabName\": \"feedback-model01-v1\"\r\n+                }\r\n+            }\r\n+        },\r\n+\r\n+        {\r\n+            \"model\": {\r\n+                \"uiPath\": \"choose-model03-v2-p10\",\r\n+                \"bundleName\": \"choose\",\r\n+                \"prefabName\": \"choose-model03-v3\",\r\n+                \"config\": {\r\n+\r\n+                    \"boxSoundUrl\": \"ui://733aoo45gzaz7j\",\r\n+\r\n+                    \"guidIndex\": 0\r\n+                    \r\n+                }\r\n+            }, \r\n+            \r\n+            \"components\": {\r\n+                \"feedback\": {\r\n+                    \"bundleName\": \"feedback\",\r\n+                    \"prefabName\": \"feedback-model01-v1\"\r\n+                }\r\n+            }\r\n+        },\r\n+\r\n+        \r\n+        {\r\n+            \"model\": {\r\n+                \"uiPath\": \"choose-model03-v2-p11\",\r\n+                \"bundleName\": \"choose\",\r\n+                \"prefabName\": \"choose-model03-v3\",\r\n+                \"config\": {\r\n+\r\n+                    \"boxSoundUrl\": \"ui://733aoo45w2qd23\",\r\n+\r\n+                    \"guidIndex\": 1\r\n+                    \r\n+                }\r\n+            }, \r\n+            \r\n+            \"components\": {\r\n+                \"feedback\": {\r\n+                    \"bundleName\": \"feedback\",\r\n+                    \"prefabName\": \"feedback-model01-v1\"\r\n+                }\r\n+            }\r\n+        },\r\n+\r\n+        {\r\n+            \"model\": {\r\n+              \"uiPath\": \"static-model01-v1-p12\",\r\n+              \"bundleName\": \"static\",\r\n+              \"prefabName\": \"static-model01-v1\"\r\n+            }\r\n+          }\r\n+\r\n+\r\n+    ]\r\n+}\n\\ No newline at end of file\n"
                }
            ],
            "date": 1623994460686,
            "name": "Commit-0",
            "content": "{\r\n    \"name\": \"数理思维\",\r\n    \"courseName\": \"t2-02\",\r\n    \"env\": \"test\",\r\n    \"totalPages\": 12,\r\n    \"pathConfig\": {\r\n        \"remoteUrl\": \"https://6166-after-school-review-8cguaeaace9d-1304725138.tcb.qcloud.la/\",\r\n        \"controllerBundlePath\": \"T-series/prefabLibrary/controllers/\",\r\n        \"controllerName\": \"controller-model02\",\r\n        \"resourceBundlePath\": \"T-series/fairyUis/t2/\",\r\n        \"panelBundlePath\": \"T-series/prefabLibrary/components/\",\r\n        \"panelName\": \"formal-panle-model02\",\r\n        \"modelBundlePath\": \"T-series/prefabLibrary/models/\",\r\n        \"componentBundlePath\": \"T-series/prefabLibrary/components/\",\r\n        \"resourceName\": \"t2-02\",\r\n        \"packageName\": \"t2-02\"\r\n    },\r\n    \"chapters\": [ \r\n        \r\n        {\r\n            \"model\": {\r\n              \"uiPath\": \"static-model01-v1-p1\",\r\n              \"bundleName\": \"static\",\r\n              \"prefabName\": \"static-model01-v1\"\r\n            }\r\n        },\r\n\r\n        {\r\n            \"model\": {\r\n                \"uiPath\": \"choose-model03-v1-p2\",\r\n                \"bundleName\": \"choose\",\r\n                \"prefabName\": \"choose-model03-v1\",\r\n                \"config\": {\r\n                    \"isAnimateShow\": true,\r\n                    \"soundFile\": {\"piano\": \"ui://733aoo45w2qd18\", \"gu\": \"ui://733aoo45w2qd16\", \"shachui\": \"ui://733aoo45w2qd1a\", \"dizi\": \"ui://733aoo45w2qd17\", \"sanjiaotie\": \"ui://733aoo45w2qd19\" },\r\n                    \"rightSoundFile\": [\"ui://733aoo45w2qd18\", \"ui://733aoo45w2qd16\"],\r\n                    \"animateName\":{\"piano\": {\"idle\": \"05gangqin_idle\", \"play\": \"05gangqin_play\", \"skin\": \"05gangqin\"},\"gu\": {\"idle\": \"01gu_idle\", \"play\": \"01gu_play\", \"skin\": \"01gu\"},\"shachui\": {\"idle\": \"02shacui_idle\", \"play\": \"02shacui_play\", \"skin\": \"02shacui\"},\r\n                    \"dizi\": {\"idle\": \"03dizi_idle\", \"play\": \"03dizi_play\", \"skin\": \"03dizi\"},\r\n                    \"sanjiaotie\": {\"idle\": \"04qiaojibang_idle\", \"play\": \"04qiaojibang_play\", \"skin\": \"04qiaojibang\"}},\r\n                    \"rightName\": [\"piano\", \"gu\"],\r\n                    \"optionsRect\":{\r\n                     \"piano\": {\"x\": 1237, \"y\": 653, \"width\":260, \"height\": 220},\r\n                     \"gu\": {\"x\": 495, \"y\": 200, \"width\":260, \"height\": 220},\r\n                      \"shachui\": {\"x\": 1205, \"y\": 190, \"width\":260, \"height\": 220}, \r\n                      \"dizi\": {\"x\": 850, \"y\": 440, \"width\":260, \"height\": 220}, \r\n                      \"sanjiaotie\": {\"x\": 520, \"y\": 695, \"width\":260, \"height\": 220}\r\n                    }\r\n                }\r\n            }, \r\n            \r\n            \"components\": {\r\n                \"feedback\": {\r\n                    \"bundleName\": \"feedback\",\r\n                    \"prefabName\": \"feedback-model01-v1\"\r\n                }\r\n            }\r\n        },\r\n\r\n        {\r\n            \"model\": {\r\n                \"uiPath\": \"choose-model03-v1-p3\",\r\n                \"bundleName\": \"choose\",\r\n                \"prefabName\": \"choose-model03-v1\",\r\n                \"config\": {\r\n\r\n                    \"rightName\": [\"piano\", \"gu\"],\r\n\r\n                    \"optionsRect\": {\"piano\": {\"x\": 1205, \"y\": 190, \"width\":260, \"height\": 220},\r\n                     \"gu\": {\"x\": 850, \"y\": 440, \"width\":260, \"height\": 220},\r\n                      \"shachui\": {\"x\": 520, \"y\": 695, \"width\":260, \"height\": 220}, \r\n                      \"dizi\": {\"x\": 1237, \"y\": 653, \"width\":260, \"height\": 220}, \r\n                      \"sanjiaotie\": {\"x\": 495, \"y\": 200, \"width\":260, \"height\": 220}}\r\n                }\r\n            }, \r\n            \r\n            \"components\": {\r\n                \"feedback\": {\r\n                    \"bundleName\": \"feedback\",\r\n                    \"prefabName\": \"feedback-model01-v1\"\r\n                }\r\n            }\r\n        },\r\n\r\n        {\r\n            \"model\": {\r\n                \"uiPath\": \"choose-model03-v1-p4\",\r\n                \"bundleName\": \"choose\",\r\n                \"prefabName\": \"choose-model03-v1\",\r\n                \"config\": {\r\n                    \r\n                    \"rightName\": [\"piano\", \"gu\"],\r\n                    \"optionsRect\": {\"piano\": {\"x\": 850, \"y\": 440, \"width\":260, \"height\": 220}, \r\n                     \"gu\": {\"x\": 520, \"y\": 695, \"width\":260, \"height\": 220},\r\n                      \"shachui\": {\"x\": 495, \"y\": 200, \"width\":260, \"height\": 220}, \r\n                      \"dizi\": {\"x\": 1205, \"y\": 190, \"width\":260, \"height\": 220}, \r\n                      \"sanjiaotie\": {\"x\": 1237, \"y\": 653, \"width\":260, \"height\": 220}}\r\n                }\r\n            }, \r\n            \r\n            \"components\": {\r\n                \"feedback\": {\r\n                    \"bundleName\": \"feedback\",\r\n                    \"prefabName\": \"feedback-model01-v1\"\r\n                }\r\n            }\r\n        },\r\n\r\n        {\r\n            \"model\": {\r\n                \"uiPath\": \"choose-model03-v2-p5\",\r\n                \"bundleName\": \"choose\",\r\n                \"prefabName\": \"choose-model03-v2\",\r\n                \"config\": {\r\n                    \"gameFood\": [\"food_1\", \"food_2\", \"food_3\", \"food_4\"],\r\n                    \"rightIndexs\": [0, 1],\r\n                    \"boySoundPath\": \"ui://733aoo45w2qd1c\",\r\n                    \"girlSoundPath\": \"ui://733aoo45w2qd1d\"\r\n                    \r\n                }\r\n            }, \r\n            \r\n            \"components\": {\r\n                \"feedback\": {\r\n                    \"bundleName\": \"feedback\",\r\n                    \"prefabName\": \"feedback-model01-v1\"\r\n                }\r\n            }\r\n        },\r\n\r\n        {\r\n            \"model\": {\r\n                \"uiPath\": \"choose-model03-v2-p6\",\r\n                \"bundleName\": \"choose\",\r\n                \"prefabName\": \"choose-model03-v2\",\r\n                \"config\": {\r\n                    \"gameFood\": [\"food_1_1\", \"food_2_1\", \"food_3_1\"],\r\n                    \"rightIndexs\": [0],\r\n                    \"boySoundPath\": \"ui://733aoo45gzaz7e\",\r\n                    \"girlSoundPath\": \"ui://733aoo45gzaz7f\"\r\n                    \r\n                }\r\n            }, \r\n            \r\n            \"components\": {\r\n                \"feedback\": {\r\n                    \"bundleName\": \"feedback\",\r\n                    \"prefabName\": \"feedback-model01-v1\"\r\n                }\r\n            }\r\n        },\r\n\r\n        {\r\n            \"model\": {\r\n                \"uiPath\": \"choose-model03-v2-p7\",\r\n                \"bundleName\": \"choose\",\r\n                \"prefabName\": \"choose-model03-v2\",\r\n                \"config\": {\r\n\r\n                    \"gameFood\": [\"food_1_2\", \"food_2_2\", \"food_3_2\"],\r\n                    \"rightIndexs\": [1],\r\n                    \"boySoundPath\": \"ui://733aoo45gzaz7g\",\r\n                    \"girlSoundPath\": \"ui://733aoo45gzaz7h\"\r\n                    \r\n                }\r\n            }, \r\n            \r\n            \"components\": {\r\n                \"feedback\": {\r\n                    \"bundleName\": \"feedback\",\r\n                    \"prefabName\": \"feedback-model01-v1\"\r\n                }\r\n            }\r\n        },\r\n\r\n        {\r\n            \"model\": {\r\n                \"uiPath\": \"choose-model03-v2-p8\",\r\n                \"bundleName\": \"choose\",\r\n                \"prefabName\": \"choose-model03-v3\",\r\n                \"config\": {\r\n\r\n                    \"boxSoundUrl\": \"ui://733aoo45w2qd1f\",\r\n                    \"guidIndex\": 2\r\n                    \r\n                }\r\n            }, \r\n            \r\n            \"components\": {\r\n                \"feedback\": {\r\n                    \"bundleName\": \"feedback\",\r\n                    \"prefabName\": \"feedback-model01-v1\"\r\n                }\r\n            }\r\n        },\r\n\r\n\r\n        {\r\n            \"model\": {\r\n                \"uiPath\": \"choose-model03-v2-p9\",\r\n                \"bundleName\": \"choose\",\r\n                \"prefabName\": \"choose-model03-v3\",\r\n                \"config\": {\r\n\r\n                    \"boxSoundUrl\": \"ui://733aoo45gzaz7i\",\r\n                    \"guidIndex\": 2\r\n                    \r\n                }\r\n            }, \r\n            \r\n            \"components\": {\r\n                \"feedback\": {\r\n                    \"bundleName\": \"feedback\",\r\n                    \"prefabName\": \"feedback-model01-v1\"\r\n                }\r\n            }\r\n        },\r\n\r\n        {\r\n            \"model\": {\r\n                \"uiPath\": \"choose-model03-v2-p10\",\r\n                \"bundleName\": \"choose\",\r\n                \"prefabName\": \"choose-model03-v3\",\r\n                \"config\": {\r\n\r\n                    \"boxSoundUrl\": \"ui://733aoo45gzaz7j\",\r\n\r\n                    \"guidIndex\": 0\r\n                    \r\n                }\r\n            }, \r\n            \r\n            \"components\": {\r\n                \"feedback\": {\r\n                    \"bundleName\": \"feedback\",\r\n                    \"prefabName\": \"feedback-model01-v1\"\r\n                }\r\n            }\r\n        },\r\n\r\n        \r\n        {\r\n            \"model\": {\r\n                \"uiPath\": \"choose-model03-v2-p11\",\r\n                \"bundleName\": \"choose\",\r\n                \"prefabName\": \"choose-model03-v3\",\r\n                \"config\": {\r\n\r\n                    \"boxSoundUrl\": \"ui://733aoo45w2qd23\",\r\n\r\n                    \"guidIndex\": 1\r\n                    \r\n                }\r\n            }, \r\n            \r\n            \"components\": {\r\n                \"feedback\": {\r\n                    \"bundleName\": \"feedback\",\r\n                    \"prefabName\": \"feedback-model01-v1\"\r\n                }\r\n            }\r\n        },\r\n\r\n        {\r\n            \"model\": {\r\n              \"uiPath\": \"static-model01-v1-p12\",\r\n              \"bundleName\": \"static\",\r\n              \"prefabName\": \"static-model01-v1\"\r\n            }\r\n          }\r\n\r\n    ]\r\n}"
        }
    ]
}